{
  "id": "blue-man-ai",
  "title": "Blue Man AI",
  "description": "<p>Интеграция Gemini ИИ для NPC: Живые диалоги, Торговля, Квесты и Оживление мира.</p>",
  "version": "0.13.17",
  "manifest": "",
  "compatibility": {
    "minimum": "12",
    "verified": "13"
  },
  "authors": [
    {
      "name": "Art_lex",
      "flags": {}
    }
  ],
  "esmodules": [
    "scripts/core/main.js"
  ],
  "styles": [
    {
      "src": "styles/style.css"
    }
  ],
  "relationships": {
    "systems": [
      {
        "id": "dnd5e",
        "type": "system",
        "compatibility": {
          "minimum": "4.0.0"
        }
      },
      {
        "id": "cyberpunk-red-core",
        "type": "system",
        "compatibility": {}
      }
    ]
  },
  "flags": {}
}